asgi_trailers/__init__.py
asgi_trailers/py.typed
asgi_trailers/response.py
asgi_trailers-0.1.0.dist-info/METADATA
asgi_trailers-0.1.0.dist-info/WHEEL
asgi_trailers-0.1.0.dist-info/RECORD
